stackit/opensearch/__init__.py
stackit/opensearch/api/__init__.py
stackit/opensearch/api/default_api.py
stackit/opensearch/api_client.py
stackit/opensearch/api_response.py
stackit/opensearch/configuration.py
stackit/opensearch/exceptions.py
stackit/opensearch/models/__init__.py
stackit/opensearch/models/backup.py
stackit/opensearch/models/create_backup_response_item.py
stackit/opensearch/models/create_instance_payload.py
stackit/opensearch/models/create_instance_response.py
stackit/opensearch/models/credentials.py
stackit/opensearch/models/credentials_list_item.py
stackit/opensearch/models/credentials_response.py
stackit/opensearch/models/error.py
stackit/opensearch/models/get_metrics_response.py
stackit/opensearch/models/instance.py
stackit/opensearch/models/instance_last_operation.py
stackit/opensearch/models/instance_parameters.py
stackit/opensearch/models/instance_schema.py
stackit/opensearch/models/list_backups_response.py
stackit/opensearch/models/list_credentials_response.py
stackit/opensearch/models/list_instances_response.py
stackit/opensearch/models/list_offerings_response.py
stackit/opensearch/models/list_restores_response.py
stackit/opensearch/models/model_schema.py
stackit/opensearch/models/offering.py
stackit/opensearch/models/partial_update_instance_payload.py
stackit/opensearch/models/plan.py
stackit/opensearch/models/raw_credentials.py
stackit/opensearch/models/restore.py
stackit/opensearch/models/trigger_restore_response.py
stackit/opensearch/models/update_backups_config_payload.py
stackit/opensearch/models/update_backups_config_response.py
stackit/opensearch/py.typed
stackit/opensearch/rest.py
stackit_opensearch-0.4.0.dist-info/LICENSE.md
stackit_opensearch-0.4.0.dist-info/METADATA
stackit_opensearch-0.4.0.dist-info/NOTICE.txt
stackit_opensearch-0.4.0.dist-info/WHEEL
stackit_opensearch-0.4.0.dist-info/RECORD
